Metadata-Version: 1.0
Name: django-forgiving-collectstatic
Version: 1.0.0
Summary: An extension of the django.contrib.staticfiles.storage.ManifestStaticFilesStorage that skips missing files and assets during the python manage.py collectstatic command run.
Home-page: https://github.com/timonweb/django-forgiving-collectstatic
Author: Tim Kamanin
Author-email: tim@timonweb.com
License: MIT
Platform: UNKNOWN
